TbaApi3
