Metadata-Version: 1.1
Name: TbaApi3
Version: 0.1a3
Summary: A Python library for the TBA API v3
Home-page: https://github.com/DanWaxman/TbaApi3
Author: Dan Waxman
Author-email: dan.waxman1@gmail.com
License: MIT
Platform: UNKNOWN
Classifier: Development Status :: 2 - Pre-Alpha
Classifier: License :: OSI Approved :: MIT License
Classifier: Natural Language :: English
